bbox_visualizer/__init__.py
bbox_visualizer/core/__init__.py
bbox_visualizer/core/_utils.py
bbox_visualizer/core/flags.py
bbox_visualizer/core/labels.py
bbox_visualizer/core/rectangle.py
bbox_visualizer-0.2.2.dist-info/METADATA
bbox_visualizer-0.2.2.dist-info/WHEEL
bbox_visualizer-0.2.2.dist-info/licenses/LICENSE
bbox_visualizer-0.2.2.dist-info/RECORD
