Metadata-Version: 2.4
Name: bbox_visualizer
Version: 0.2.2
Summary: Different ways of visualizing objects given bounding box data
Project-URL: Homepage, https://github.com/shoumikchow/bbox-visualizer
Project-URL: Repository, https://github.com/shoumikchow/bbox-visualizer
Project-URL: Documentation, https://bbox-visualizer.readthedocs.io
Project-URL: Issues, https://github.com/shoumikchow/bbox-visualizer/issues
Project-URL: Changelog, https://github.com/shoumikchow/bbox-visualizer/releases
Author-email: Shoumik Sharar Chowdhury <shoumikchow@gmail.com>
License-Expression: MIT
License-File: LICENSE
Keywords: bbox_visualizer,bounding-box,computer-vision,visualization
Classifier: Development Status :: 4 - Beta
Classifier: Intended Audience :: Developers
Classifier: License :: OSI Approved :: MIT License
Classifier: Natural Language :: English
Classifier: Programming Language :: Python :: 3
Classifier: Programming Language :: Python :: 3.9
Classifier: Programming Language :: Python :: 3.10
Classifier: Programming Language :: Python :: 3.11
Classifier: Programming Language :: Python :: 3.12
Classifier: Topic :: Scientific/Engineering :: Image Processing
Classifier: Topic :: Scientific/Engineering :: Visualization
Requires-Python: >=3.9
Requires-Dist: numpy>=1.19.0
Requires-Dist: opencv-python>=4.1.0.25
Provides-Extra: dev
Requires-Dist: build>=1.0.3; extra == 'dev'
Requires-Dist: hatch>=1.7.0; extra == 'dev'
Requires-Dist: pytest>=7.4.0; extra == 'dev'
Requires-Dist: ruff>=0.2.1; extra == 'dev'
Requires-Dist: twine>=4.0.2; extra == 'dev'
Provides-Extra: docs
Requires-Dist: docutils>=0.20.1; extra == 'docs'
Requires-Dist: myst-parser>=2.0.0; extra == 'docs'
Requires-Dist: sphinx-autodoc-typehints>=1.24.0; extra == 'docs'
Requires-Dist: sphinx-copybutton>=0.5.2; extra == 'docs'
Requires-Dist: sphinx-rtd-theme>=2.0.0; extra == 'docs'
Requires-Dist: sphinx>=7.0.0; extra == 'docs'
Provides-Extra: examples
Requires-Dist: matplotlib; extra == 'examples'
Requires-Dist: notebook; extra == 'examples'
